tcanvas/__init__.py
tcanvas/tcanvas.py
tcanvas/test_all.py
tcanvas/version.py
tcanvas-0.0.1.dist-info/LICENSE
tcanvas-0.0.1.dist-info/METADATA
tcanvas-0.0.1.dist-info/WHEEL
tcanvas-0.0.1.dist-info/top_level.txt
tcanvas-0.0.1.dist-info/RECORD
