Metadata-Version: 2.1
Name: tcanvas
Version: 0.0.1
Summary: Text based canvases.
Home-page: https://github.com/ast0815/tcanvas
Author: Lukas Koch
Author-email: lukas.koch@mailbox.org
License: MIT
Platform: UNKNOWN
Classifier: Development Status :: 3 - Alpha
Classifier: Intended Audience :: Developers
Classifier: License :: OSI Approved :: MIT License
Classifier: Operating System :: Microsoft :: Windows
Classifier: Operating System :: MacOS
Classifier: Operating System :: POSIX
Classifier: Operating System :: Unix
Classifier: Programming Language :: Python
Classifier: Programming Language :: Python :: 2.7
Classifier: Programming Language :: Python :: 3.5
Classifier: Programming Language :: Python :: 3.6
Classifier: Programming Language :: Python :: 3.7
Classifier: Programming Language :: Python :: 3.8
Classifier: Topic :: Software Development
Classifier: Topic :: Utilities
Requires-Python: !=3.0,!=3.1,!=3.2,!=3.3,!=3.4,>=2.7
Requires-Dist: click (>=7.0.0)
Provides-Extra: test
Requires-Dist: pytest (>=4.6) ; extra == 'test'
